booking/__init__.py
booking/sdk.py
booking/hooks/__init__.py
booking/hooks/hook.py
booking/models/__init__.py
booking/models/allocation_input_dto.py
booking/models/alternative_key_location_dto.py
booking/models/base.py
booking/models/bed_configuration_dto.py
booking/models/bed_dto.py
booking/models/bed_option_dto.py
booking/models/bedroom_dto.py
booking/models/block_availability_input_dto.py
booking/models/block_availability_output_dto.py
booking/models/block_output_dto.py
booking/models/booker_input_dto.py
booking/models/cancellation_dto.py
booking/models/charge_dto.py
booking/models/checkin_checkout_times_dto.py
booking/models/constant_input_dto.py
booking/models/contact_dto.py
booking/models/contacts_dto.py
booking/models/coordinates.py
booking/models/coordinates_dto.py
booking/models/cribs_and_extra_beds_dto.py
booking/models/deal_dto.py
booking/models/description_dto.py
booking/models/details_input_dto.py
booking/models/details_output_dto.py
booking/models/extra_charges_dto_double.py
booking/models/extra_charges_dto_list_charge_dto.py
booking/models/facility_dto.py
booking/models/get_accommodation_constants_accept.py
booking/models/get_block_availability_accept.py
booking/models/get_hotel_availability_accept.py
booking/models/get_hotel_theme_types_accept.py
booking/models/get_hotel_types_accept.py
booking/models/get_hotels_accept.py
booking/models/get_hotels_review_scores_accept.py
booking/models/get_room_facility_types_accept.py
booking/models/guests_input_dto.py
booking/models/hotel_availability_input_dto.py
booking/models/hotel_availability_output_dto.py
booking/models/hotel_data_dto.py
booking/models/hotel_facility_input_dto.py
booking/models/hotel_facility_type_output_dto.py
booking/models/hotel_photo_dto.py
booking/models/hotel_theme_type_input_dto.py
booking/models/hotel_theme_types_output_dto.py
booking/models/hotel_type_input_dto.py
booking/models/hotel_types_output_dto.py
booking/models/hotels_input_dto.py
booking/models/hotels_output_dto.py
booking_client-1.0.0.dist-info/LICENSE
booking_client-1.0.0.dist-info/METADATA
booking_client-1.0.0.dist-info/WHEEL
booking_client-1.0.0.dist-info/top_level.txt
booking_client-1.0.0.dist-info/RECORD
