Metadata-Version: 2.1
Name: booking-client
Version: 1.0.0
Summary: Partner Connect API Service 
License: MIT
Requires-Python: >=3.7
License-File: LICENSE
Requires-Dist: requests >=2.31.0
